<?xml version = '1.0' encoding = 'UTF-8'?>
<DataTypesDesign class="oracle.dbtools.crest.model.design.datatypes.DataTypesDesign" name="DataTypes" id="2C8DC9EB-6078-C821-59F5-4E1A71829DDF" mainViewID="1A06CA85-C112-4EA7-73CF-838F3337A7AB">
<createdBy>GGG</createdBy>
<createdTime>2026-04-06 05:36:59 UTC</createdTime>
<ownerDesignName>hr</ownerDesignName>
<shouldBeOpen>false</shouldBeOpen>
<collectionOfRefsPrefix>array_ref_</collectionOfRefsPrefix>
<collectionPrefix>array_</collectionPrefix>
<defaultArrayLimit>10</defaultArrayLimit>
<defaultCollectionType_Kind>ARRAY</defaultCollectionType_Kind>
<defaultCollectionType_Suffix>_Array</defaultCollectionType_Suffix>
<embeddedStructuredTypePrefix>inst_</embeddedStructuredTypePrefix>
<referencePrefix>ref_</referencePrefix>
<useRoleInAssociationEndAsName>true</useRoleInAssociationEndAsName>
</DataTypesDesign>